pyvesyncakerl/__init__.py
pyvesyncakerl/helpers.py
pyvesyncakerl/vesync.py
pyvesyncakerl/vesyncbasedevice.py
pyvesyncakerl/vesyncbulb.py
pyvesyncakerl/vesyncfan.py
pyvesyncakerl/vesynckitchen.py
pyvesyncakerl/vesyncoutlet.py
pyvesyncakerl/vesyncswitch.py
pyvesyncakerl-3.0.1.dist-info/LICENSE
pyvesyncakerl-3.0.1.dist-info/METADATA
pyvesyncakerl-3.0.1.dist-info/WHEEL
pyvesyncakerl-3.0.1.dist-info/top_level.txt
pyvesyncakerl-3.0.1.dist-info/RECORD
