Metadata-Version: 2.1
Name: pyvesyncakerl
Version: 3.0.1
Summary: pyvesyncakerl is a library to manage Etekcity                 Devices, Cosori Air Fryers and Levoit Air                      Purifiers run on the VeSync app.
Home-page: https://github.com/webdjoe/pyvesyncakerl
Author: Mark Perdue, Joe Trabulsy
Author-email: webdjoe@gmail.com
License: MIT
Keywords: iot,vesync,levoit,etekcity,cosori,valceno
Classifier: License :: OSI Approved :: MIT License
Classifier: Intended Audience :: Developers
Classifier: Intended Audience :: End Users/Desktop
Classifier: Natural Language :: English
Classifier: Programming Language :: Python :: 3.8
Requires-Python: >=3.8
License-File: LICENSE
Requires-Dist: requests >=2.20.0
Provides-Extra: dev
Requires-Dist: pytest ; extra == 'dev'
Requires-Dist: pytest-cov ; extra == 'dev'
Requires-Dist: yaml ; extra == 'dev'
Requires-Dist: tox ; extra == 'dev'
